[
    {
        "language": "it",
        "page": "navbar",
        "content": "REGISTRA",
        "additional": "/record"
    },
    {
        "language": "it",
        "page": "navbar",
        "content": "VALUTA",
        "additional": "/evaluate"
    },
    {
        "language": "it",
        "page": "navbar",
        "content": "DATABASE",
        "additional": "/database"
    },
    {
        "language": "it",
        "page": "navbar",
        "content": "CHI SIAMO",
        "additional": "/about-us"
    },



    {
        "language": "en",
        "page": "navbar",
        "content": "RECORD",
        "additional": "/record"
    },
    {
        "language": "en",
        "page": "navbar",
        "content": "EVALUATE",
        "additional": "/evaluate"
    },
    {
        "language": "en",
        "page": "navbar",
        "content": "DATABASE",
        "additional": "/database"
    },
    {
        "language": "en",
        "page": "navbar",
        "content": "ABOUT US",
        "additional": "/about-us"
    },

















    {
        "language": "it",
        "page": "home",
        "position": "landing-title",
        "content": "Esprimiamo le nostre emozioni, insieme."
    },
    {
        "language": "it",
        "page": "home",
        "position": "landing-subtitle",
        "content": "Parla, valuta e gioca con noi per insegnare ai computer come riconoscere le emozioni."
    },
    {
        "language": "it",
        "page": "home",
        "position": "landing-btn-sx",
        "content": "Registra"
    },
    {
        "language": "it",
        "page": "home",
        "position": "landing-btn-sub-sx",
        "content": "Registra la tua voce esprimendo un'emozione da te scelta"
    },
    {
        "language": "it",
        "page": "home",
        "position": "landing-btn-dx",
        "content": "Valuta"
    },
    {
        "language": "it",
        "page": "home",
        "position": "landing-btn-sub-dx",
        "content": "Ascolta la voce di altre persone e valuta quale emozione hanno voluto esprimere"
    },
    {
        "language": "it",
        "page": "home",
        "position": "cards-sx-title",
        "content": "Registra la tua voce"
    },
    {
        "language": "it",
        "page": "home",
        "position": "cards-sx-subtitle",
        "content": "Il nostro obiettivo è quello di utilizzare il crowdsourcing per raccogliere il più grande numero di sample vocali contenenti delle emozioni 'vere' create da persone reali, come te"
    },
    {
        "language": "it",
        "page": "home",
        "position": "cards-center-title",
        "content": "Ascolta e valuta"
    },
    {
        "language": "it",
        "page": "home",
        "position": "cards-center-subtitle",
        "content": "La quantità di registrazioni sarebbe inutile senza una validazione. Grazie alle stesse persone che hanno messo a disposizione la propria voce, vogliamo selezionare i sample migliori"
    },
    {
        "language": "it",
        "page": "home",
        "position": "cards-dx-title",
        "content": "Un database accessibile"
    },
    {
        "language": "it",
        "page": "home",
        "position": "cards-dx-subtitle",
        "content": "Tutto ciò che facciamo è per aiutare la ricerca e migliorarla. Per questo il database che vogliamo creare sarà universalmente disponibile, così che chiunque possa ottenere grandi risultati in poco tempo"
    },
    {
        "language": "it",
        "page": "home",
        "position": "graphic-safety",
        "content": "<h2>I tuoi dati sono in buone mani</h2><p style='text-align: right'>I pochi dati che ti chiederemo serviranno solamente per arricchire la nostra ricerca e dare un valore aggiunto alle registrazioni. Nessun dato che ci consegnerai verrà utilizzato al di fuori dell'ambito scientifico</p>"
    },
    {
        "language": "it",
        "page": "home",
        "position": "graphic-deep-learning",
        "content": "<h2>La potenza di questa ricerca</h2><p style='text-align: left'>Lo sviluppo delle reti neurali e del Deep Learning al giorno d'oggi ci permette di utilizzare i dati raccolti nei modi più disparati. I sample che raccogliamo serviranno per insegnare alle macchine a riconoscere le emozioni instrinseche nel parlato umano e quindi aiutare persone che si trovano in difficoltà quando si tratta di fare qualcosa di (apparentemente) così semplice: <strong>esprimere le proprie emozioni</strong></p>"
    },



    {
        "language": "en",
        "page": "home",
        "position": "landing-title",
        "content": "Let's be emotional, together."
    },
    {
        "language": "en",
        "page": "home",
        "position": "landing-subtitle",
        "content": "Speak, evaluate and play to help machines recognize our emotions."
    },
    {
        "language": "en",
        "page": "home",
        "position": "landing-btn-sx",
        "content": "Record"
    },
    {
        "language": "en",
        "page": "home",
        "position": "landing-btn-sub-sx",
        "content": "Registra la tua voce esprimendo un'emozione da te scelta"
    },
    {
        "language": "en",
        "page": "home",
        "position": "landing-btn-dx",
        "content": "Evaluate"
    },
    {
        "language": "en",
        "page": "home",
        "position": "landing-btn-sub-dx",
        "content": "Ascolta la voce di altre persone e valuta quale emozione hanno voluto esprimere"
    },
    {
        "language": "en",
        "page": "home",
        "position": "cards-sx-title",
        "content": "cards-sx-title-en"
    },
    {
        "language": "en",
        "page": "home",
        "position": "cards-sx-subtitle",
        "content": "cards-sx-subtitle-en"
    },
    {
        "language": "en",
        "page": "home",
        "position": "cards-center-title",
        "content": "cards-cn-title-en"
    },
    {
        "language": "en",
        "page": "home",
        "position": "cards-center-subtitle",
        "content": "cards-cs-subtitle-en"
    },
    {
        "language": "en",
        "page": "home",
        "position": "cards-dx-title",
        "content": "cards-dx-title-en"
    },
    {
        "language": "en",
        "page": "home",
        "position": "cards-dx-subtitle",
        "content": "cards-dx-subtitle-en"
    },
    {
        "language": "en",
        "page": "home",
        "position": "graphic-title",
        "content": "graphic-title-en"
    },
    {
        "language": "en",
        "page": "home",
        "position": "graphic-subtitle",
        "content": "graphic-subtitle-en"
    },
















    {
        "language": "it",
        "page": "aboutus",
        "position": "cards-sx",
        "content": "Politecnico di Milano è un'università con sede nella città di Milano"
    },
    {
        "language": "it",
        "page": "aboutus",
        "position": "cards-sx-btn",
        "content": "Contattaci",
        "additional": "/contact-us"
    },
    {
        "language": "it",
        "page": "aboutus",
        "position": "cards-dx",
        "content": "Questo database vuole raccogliere sample vocali da poter utilizzare per il riconoscimento delle emozioni attraverso l'uso del deep learning"
    },
    {
        "language": "it",
        "page": "aboutus",
        "position": "cards-dx-btn",
        "content": "Contribuisci",
        "additional": "/contribute"
    },



    {
        "language": "en",
        "page": "aboutus",
        "position": "cards-sx",
        "content": "Politecnico di Milano is a university based in Milan"
    },
    {
        "language": "en",
        "page": "aboutus",
        "position": "cards-sx-btn",
        "content": "CONTACT US",
        "additional": "/contact-us"
    },
    {
        "language": "en",
        "page": "aboutus",
        "position": "cards-dx",
        "content": "This database wants to collect voice samples that can be used to recognize emotions through the application of deep learning"
    },
    {
        "language": "en",
        "page": "aboutus",
        "position": "cards-dx-btn",
        "content": "CONTRIBUTE",
        "additional": "/contribute"
    },














    {
        "language": "it",
        "page": "faq",
        "content": "The samples will be used to help reasearchers find new technological solutions",
        "additional": "Risposta del faq"
    },
    {
        "language": "it",
        "page": "faq",
        "content": "Qualcosa d'altro",
        "additional": "Risposta del faq"
    },
    {
        "language": "en",
        "page": "faq",
        "content": "The samples will be used to help reasearchers find new technological solutions",
        "additional": "Answer to faq"
    },
    {
        "language": "en",
        "page": "faq",
        "content": "The samples will be used to help reasearchers find new technological solutions",
        "additional": "Answer to faq"
    },






    {
        "language": "en",
        "page": "recordguide",
        "content": "Something"
    },
    {
        "language": "it",
        "page": "recordguide",
        "content": "<p style='margin: 0px 0px 8px'>Vogliamo iniziare a registrare?</p> <p style='margin: 0px 0px 8px'>Prima di tutto, assicurati di trovarti in una stanza <strong>silenziosa</strong> per evitare rumori di sottofondo. Inoltre, per tirar fuori il meglio di te, <strong>cerca di immergerti totalmente nell'emozione</strong> che vuoi esprimere pensando ad un momento in cui hai provato l'emozione in questione (per saperne di più vedi <a href='https://it.wikipedia.org/wiki/Metodo_Stanislavskij' target='_blank'>Metodo Stanislavski</a>).</p> <strong>Buon divertimento!</strong>"
    },






    {
        "language": "en",
        "page": "evaluateguide",
        "content": "Something"
    },
    {
        "language": "it",
        "page": "evaluateguide",
        "content": "<p style='margin: 0px 0px 8px'>Sei pronto a valutare come se la cavano altre persone come te?</p> <p style='margin: 0px 0px 8px'><strong>Ascolta</strong> il sample vocale interamente cercando di identificare l'emozione che l'utente ha voluto esprimere. Seleziona poi quale emozione per te è quella più adatta a descrivere ciò che hai ascoltato e valuta la qualità della registrazione (per esempio, segnala un sample registrato in una stanza rumorosa o che non rispetta la frase esposta).</p> <strong>Buon divertimento!</strong>"
    },









    {
        "language": "it",
        "page": "recordcompleted",
        "content": "Grazie per aver contribuito alla costruzione di questo database! Continua ad esprimere le tue emozioni con noi"
    },
    {
        "language": "en",
        "page": "recordcompleted",
        "content": "Lorem ipsum is simply dummy text of the printing and typesetting industry. Lorem Ipsum has been the industry's standard dummy text ever since the 1500s, when an unknown printer took a galley of type and scrambled it to make a type specimen book. It has survived not only five centuries, but also the leap into electronic typesetting, remaining essentially unchanged."
    },








    {
        "language": "it",
        "page": "evaluationcompleted",
        "content": "Lorem ipsum is simply dummy text of the printing and typesetting industry. Lorem Ipsum has been the industry's standard dummy text ever since the 1500s, when an unknown printer took a galley of type and scrambled it to make a type specimen book. It has survived not only five centuries, but also the leap into electronic typesetting, remaining essentially unchanged."
    },
    {
        "language": "en",
        "page": "evaluationcompleted",
        "content": "Lorem ipsum is simply dummy text of the printing and typesetting industry. Lorem Ipsum has been the industry's standard dummy text ever since the 1500s, when an unknown printer took a galley of type and scrambled it to make a type specimen book. It has survived not only five centuries, but also the leap into electronic typesetting, remaining essentially unchanged."
    }













]