[
	{
		"language": "it",
		"sentence": "Mi chiamo Luca e sono un gattino"
	},
	{
		"language": "it",
		"sentence": "Torno a lavorare, ci sentiamo dopo amici miei"
	},
	{
		"language": "it",
		"sentence": "Odio la natura, preferisco la vita in città"
	},
	{
		"language": "it",
		"sentence": "Dio è un'invenzione dei potenti per controllare le masse"
	},
	{
		"language": "it",
		"sentence": "L’estate scorsa ho perso una scommessa"
	},
	{
		"language": "it",
		"sentence": "Sono stato costretto a stare in piedi sul finestrino di una macchina"
	},
	{
		"language": "it",
		"sentence": "Ho lasciato una scia sull’asfalto"
	},
	{
		"language": "it",
		"sentence": "Quel pezzo di terra è di mia proprietà"
	},
	{
		"language": "it",
		"sentence": "Sono il re del continente Africano"
	},
	{
		"language": "it",
		"sentence": "Che bella la vita a quattro zampe"
	},
	{
		"language": "it",
		"sentence": "I camionisti guidano a piedi scalzi"
	},
	{
		"language": "it",
		"sentence": "Il clima in Olanda mi turba"
	},
	{
		"language": "it",
		"sentence": "Andrea ci regalerà tanti detersivi"
	},
	{
		"language": "it",
		"sentence": "Spero che ci dia anche altri oggetti utili"
	},
	{
		"language": "it",
		"sentence": "Alberto non vuole fare la foto con le angurie"
	},
	{
		"language": "it",
		"sentence": "Non voglio rischiare di mangiare troppo"
	},
	{
		"language": "it",
		"sentence": "Sul bus per Sarajevo rubano gli yogurt"
	},
	{
		"language": "it",
		"sentence": "Aspetta che vado a lavarmi le mani, così sono pronto per mangiare"
	},
	{
		"language": "it",
		"sentence": "Non è scotta. Non è al dente. È cotta giusta. Che per me è sbagliato."
	},
	{
		"language": "it",
		"sentence": "Se tutti confermate, prenoto l’invito"
	},
	{
		"language": "it",
		"sentence": "Oggi piove ma non vedo la ruggine"
	},
	{
		"language": "it",
		"sentence": "Domani mi sembra il giorno giusto per ripartire"
	},
	{
		"language": "it",
		"sentence": "Mi hanno dato il nome sbagliato per la persona giusta"
	},
	{
		"language": "it",
		"sentence": "Il Duomo ha un portale gotico del Quattrocento."
	},
	{
		"language": "it",
		"sentence": "Tale cappella è ora in ristrutturazione."
	},
	{
		"language": "it",
		"sentence": "Ha avuto due figli da un matrimonio precedente."
	},
	{
		"language": "it",
		"sentence": "Ciò potrebbe fornire una spiegazione al fenomeno della cosiddetta materia oscura."
	},
	{
		"language": "it",
		"sentence": "Durante la seconda guerra mondiale si impegnò in Indocina contro l'esercito giapponese."
	},
	{
		"language": "it",
		"sentence": "Successivamente trascorse cinque anni come legato di Cesare durante le campagne in Gallia."
	},
	{
		"language": "it",
		"sentence": "Voi potete dire sempre quello che volete e io non posso mai dire niente."
	},






	{
		"language": "en",
		"sentence": "The cat was sitting in the kitchen on the blue chair"
	},
	{
		"language": "en",
		"sentence": "I love the sound of the wind"
	},
	{
		"language": "en",
		"sentence": "Last summer I went to New York with my family"
	},
	{
		"language": "en",
		"sentence": "Sometimes I see a truck passing in front of my window"
	},
	{
		"language": "en",
		"sentence": "The last century has been a moment of great development for human history"
	},
	{
		"language": "en",
		"sentence": "When the sea starts to be cold I prefer going to the swimming pool"
	},
	{
		"language": "en",
		"sentence": "The first time I had coffee it was during the first year of college"
	},
	{
		"language": "en",
		"sentence": "My favorite sport is hockey but I don't like watching it on the tv"
	}
]